timus/__init__.py
timus/__main__.py
timus_sender-0.1.1.post1.dist-info/LICENSE
timus_sender-0.1.1.post1.dist-info/METADATA
timus_sender-0.1.1.post1.dist-info/WHEEL
timus_sender-0.1.1.post1.dist-info/entry_points.txt
timus_sender-0.1.1.post1.dist-info/top_level.txt
timus_sender-0.1.1.post1.dist-info/RECORD
