Metadata-Version: 2.1
Name: timus-sender
Version: 0.1.1.post1
Summary: Timus console solution submitter
Home-page: https://github.com/kirillsulim/timus-sender
Author: Kirill Sulim
Author-email: kirillsulim@gmail.com
License: UNKNOWN
Platform: UNKNOWN
Classifier: Development Status :: 4 - Beta
Classifier: Environment :: Console
Classifier: Intended Audience :: Developers
Classifier: Programming Language :: Python :: 3
Classifier: Programming Language :: Python :: 3.6
Classifier: License :: OSI Approved :: MIT License
Classifier: Operating System :: OS Independent
Requires-Dist: requests (>=2.19.1)
